{
  "Computer Programming": [],
  "AP Computer Science Principles": [],
  "AP Computer Science": ["Computer Programming", "AP Computer Science Principles"],
  "Algebra 1": [],
  "Geometry": ["Algebra 1"],
  "Algebra 2": ["Geometry"],
  "Algebra 2 and Pre-Calculus": ["Geometry"],
  "Pre-Calculus": ["Algebra 2"],
  "Pre-Calculus Honors": ["Algebra 2"],
  "AP Statistics": ["Algebra 2", "Algebra 2 and Pre-Calculus"],
  "AP Calculus AB": ["Algebra 2 and Pre-Calculus", "Pre-Calculus", "Pre-Calculus Honors"],
  "AP Calculus BC": ["Algebra 2 and Pre-Calculus", "Pre-Calculus", "Pre-Calculus Honors"],
  "Biology": [],
  "AP Biology": ["Chemistry", "Chemistry Honors", "Biology"],
  "AP Physics 1": ["Biology"],
  "AP Physics 2": ["AP Physics 1"],
  "AP Physics C": ["AP Physics 2"],
  "Physics": ["Biology"],
  "Chemistry": ["Biology"],
  "Chemistry Honors": ["Biology"],
  "AP Chemistry": ["Chemistry", "Chemistry Honors"],
  "English 1": [],
  "English 2": ["English 1"],
  "Critical Writing": ["English 2"],
  "AP English Language and Composition": ["English 2"],
  "AP English Literature and Composition": ["AP English Language and Composition"]
}
